{
  "french": [
    {"le": {"romaji": "luh", "english": "the"}},
    {"de": {"romaji": "duh", "english": "of"}},
    {"un": {"romaji": "uhn", "english": "a"}},
    {"à": {"romaji": "ah", "english": "to"}},
    {"être": {"romaji": "etruh", "english": "to be"}},
    {"et": {"romaji": "ay", "english": "and"}},
    {"en": {"romaji": "uhn", "english": "in"}},
    {"avoir": {"romaji": "ah-vwahr", "english": "to have"}},
    {"que": {"romaji": "kuh", "english": "that"}},
    {"pour": {"romaji": "poor", "english": "for"}},
    {"dans": {"romaji": "dahn", "english": "in"}},
    {"ce": {"romaji": "suh", "english": "this"}},
    {"qui": {"romaji": "kee", "english": "who"}},
    {"ne": {"romaji": "nuh", "english": "not"}},
    {"sur": {"romaji": "sir", "english": "on"}},
    {"se": {"romaji": "suh", "english": "oneself"}},
    {"pas": {"romaji": "pah", "english": "not"}},
    {"plus": {"romaji": "pluh", "english": "more"}},
    {"pouvoir": {"romaji": "poo-vwahr", "english": "to be able to"}},
    {"par": {"romaji": "par", "english": "by"}},
    {"je": {"romaji": "zhuh", "english": "I"}},
    {"avec": {"romaji": "ah-vehk", "english": "with"}},
    {"tout": {"romaji": "toot", "english": "all"}},
    {"faire": {"romaji": "fehr", "english": "to do"}},
    {"son": {"romaji": "sohn", "english": "his"}},
    {"mettre": {"romaji": "meh-truh", "english": "to put"}},
    {"autre": {"romaji": "oh-tr", "english": "other"}},
    {"on": {"romaji": "ohn", "english": "one"}},
    {"mais": {"romaji": "meh", "english": "but"}},
    {"nous": {"romaji": "noo", "english": "we"}},
    {"comme": {"romaji": "kohm", "english": "like"}},
    {"ou": {"romaji": "oo", "english": "or"}},
    {"si": {"romaji": "see", "english": "if"}},
    {"leur": {"romaji": "luhr", "english": "their"}},
    {"y": {"romaji": "ee", "english": "there"}},
    {"dire": {"romaji": "deer", "english": "to say"}},
    {"elle": {"romaji": "ehl", "english": "she"}},
    {"devoir": {"romaji": "duh-vwahr", "english": "to have to"}},
    {"prendre": {"romaji": "prahdruh", "english": "to take"}},
    {"aussi": {"romaji": "oh-see", "english": "also"}},
    {"deux": {"romaji": "duh", "english": "two"}},
    {"même": {"romaji": "mem", "english": "same"}},
    {"où": {"romaji": "oo", "english": "where"}},
    {"dire": {"romaji": "deer", "english": "to say"}},
    {"avant": {"romaji": "ah-vahn", "english": "before"}},
    {"même": {"romaji": "mem", "english": "same"}},
    {"voir": {"romaji": "vwahr", "english": "to see"}},
    {"quel": {"romaji": "kell", "english": "which"}},
    {"quelque": {"romaji": "kel-kuh", "english": "some"}},
    {"temps": {"romaji": "tah", "english": "time"}},
    {"si": {"romaji": "see", "english": "if"}},
    {"dire": {"romaji": "deer", "english": "to say"}},
    {"sans": {"romaji": "sahn", "english": "without"}},
    {"venir": {"romaji": "vuh-neer", "english": "to come"}},
    {"très": {"romaji": "tray", "english": "very"}},
    {"grand": {"romaji": "grahn", "english": "big"}},
    {"après": {"romaji": "ah-pray", "english": "after"}},
    {"vouloir": {"romaji": "voo-lwahr", "english": "to want"}},
    {"an": {"romaji": "ah", "english": "year"}},
    {"aller": {"romaji": "ah-lay", "english": "to go"}},
    {"déjà": {"romaji": "day-zhah", "english": "already"}},
    {"mon": {"romaji": "mohn", "english": "my"}},
    {"notre": {"romaji": "notr", "english": "our"}},
    {"bon": {"romaji": "bohn", "english": "good"}},
    {"où": {"romaji": "oo", "english": "where"}},
    {"dire": {"romaji": "deer", "english": "to say"}},
    {"alors": {"romaji": "ah-lohr", "english": "then"}},
    {"peu": {"romaji": "puh", "english": "few"}},
    {"nouveau": {"romaji": "noo-voh", "english": "new"}},
    {"savoir": {"romaji": "sah-vwahr", "english": "to know"}},
    {"quoi": {"romaji": "kwa", "english": "what"}},
    {"non": {"romaji": "noh", "english": "no"}},
    {"moment": {"romaji": "moh-mah", "english": "moment"}},
    {"jour": {"romaji": "zhur", "english": "day"}},
    {"personne": {"romaji": "pair-sohn", "english": "nobody"}},
    {"aller": {"romaji": "ah-lay", "english": "to go"}},
    {"jour": {"romaji": "zhur", "english": "day"}},
    {"donner": {"romaji": "doh-nay", "english": "to give"}},
    {"avoir": {"romaji": "ah-vwahr", "english": "to have"}},
    {"trop": {"romaji": "troh", "english": "too much"}},
    {"trouver": {"romaji": "troo-veh", "english": "to find"}},
    {"heure": {"romaji": "ur", "english": "hour"}},
    {"partir": {"romaji": "par-teer", "english": "to leave"}},
    {"venir": {"romaji": "vuh-neer", "english": "to come"}},
    {"deux": {"romaji": "duh", "english": "two"}},
    {"devoir": {"romaji": "duh-vwahr", "english": "to have to"}},
    {"vouloir": {"romaji": "voo-lwahr", "english": "to want"}},
    {"donner": {"romaji": "doh-nay", "english": "to give"}},
    {"très": {"romaji": "tray", "english": "very"}},
    {"après": {"romaji": "ah-pray", "english": "after"}},
    {"bien": {"romaji": "byehn", "english": "well"}},
    {"seulement": {"romaji": "suh-luh-mahn", "english": "only"}},
    {"falloir": {"romaji": "fah-lwahr", "english": "to be necessary"}},
    {"encore": {"romaji": "ahn-kor", "english": "again"}},
    {"ainsi": {"romaji": "ahn-see", "english": "thus"}},
    {"venir": {"romaji": "vuh-neer", "english": "to come"}},
    {"croire": {"romaji": "krwahr", "english": "to believe"}},
    {"demander": {"romaji": "duh-mahn-day", "english": "to ask"}},
    {"entendre": {"romaji": "ohn-tahndruh", "english": "to hear"}},
    {"travail": {"romaji": "trah-vahy", "english": "work"}},
    {"rester": {"romaji": "ruh-stay", "english": "to stay"}},
    {"placer": {"romaji": "plah-say", "english": "to place"}},
    {"suite": {"romaji": "sweet", "english": "suite"}},
    {"peu": {"romaji": "puh", "english": "few"}},
    {"monde": {"romaji": "mohnd", "english": "world"}}
  ]
}
